backy_db/__init__.py
backy_db/compression/__init__.py
backy_db/compression/compression_base.py
backy_db/compression/compression_manager.py
backy_db/compression/tar_compression.py
backy_db/compression/zip_compression.py
backy_db/config_schemas/__init__.py
backy_db/config_schemas/validator.py
backy_db/config_schemas/schemas/__init__.py
backy_db/config_schemas/schemas/backup_info_schema.py
backy_db/config_schemas/schemas/backup_schema.py
backy_db/config_schemas/schemas/compression_schema.py
backy_db/config_schemas/schemas/database_schema.py
backy_db/config_schemas/schemas/integrity_schema.py
backy_db/config_schemas/schemas/restore_schema.py
backy_db/config_schemas/schemas/security_schema.py
backy_db/config_schemas/schemas/storage_schema.py
backy_db/databases/__init__.py
backy_db/databases/database_base.py
backy_db/databases/database_context.py
backy_db/databases/database_manager.py
backy_db/databases/database_utils.py
backy_db/databases/mysql/__init__.py
backy_db/databases/mysql/mysql_manager.py
backy_db/databases/mysql/mysql_restore.py
backy_db/databases/mysql/mysql_sorting.py
backy_db/databases/mysql/mysql_streaming.py
backy_db/databases/mysql/mysql_utils.py
backy_db/integrity/__init__.py
backy_db/integrity/checksum_integrity.py
backy_db/integrity/hmac_integrity.py
backy_db/integrity/integrity_base.py
backy_db/integrity/integrity_manager.py
backy_db/io_engine/__init__.py
backy_db/io_engine/data_converter.py
backy_db/io_engine/io_creator.py
backy_db/io_engine/stream/__init__.py
backy_db/io_engine/stream/read_stream.py
backy_db/io_engine/stream/stream_base.py
backy_db/io_engine/stream/write_stream.py
backy_db/logger/__init__.py
backy_db/logger/logger_manager.py
backy_db/manager/__init__.py
backy_db/manager/backup_manager.py
backy_db/manager/backy_db.py
backy_db/manager/manager_context.py
backy_db/manager/restore_manager.py
backy_db/metadata/__init__.py
backy_db/metadata/creation_metadata.py
backy_db/metadata/extraction_metadata.py
backy_db/security/__init__.py
backy_db-0.1.0.dist-info/METADATA
backy_db-0.1.0.dist-info/WHEEL
backy_db-0.1.0.dist-info/top_level.txt
backy_db-0.1.0.dist-info/RECORD
