Metadata-Version: 2.4
Name: backy-db
Version: 0.1.0
Summary: Modular, secure database backup and restore system with MySQL support
Author-email: Amgad Fikry Mohamed <dr.amgad_sh92@yahoo.com>
License: MIT
Requires-Python: >=3.10
Requires-Dist: pydantic>=2.0
Requires-Dist: PyYAML
Requires-Dist: python-dotenv
Requires-Dist: mysql-connector-python
Requires-Dist: sqlparse
Requires-Dist: cryptography>=42.0.0
Provides-Extra: aws
Requires-Dist: boto3; extra == "aws"
Provides-Extra: gcp
Requires-Dist: google-api-core; extra == "gcp"
Requires-Dist: google-auth; extra == "gcp"
Requires-Dist: google-cloud-secret-manager; extra == "gcp"
Requires-Dist: google-cloud-storage; extra == "gcp"
Requires-Dist: grpc-google-iam-v1; extra == "gcp"
Requires-Dist: grpcio; extra == "gcp"
Requires-Dist: grpcio-status; extra == "gcp"
Requires-Dist: proto-plus; extra == "gcp"
Requires-Dist: protobuf; extra == "gcp"
Provides-Extra: full
Requires-Dist: boto3; extra == "full"
Requires-Dist: google-api-core; extra == "full"
Requires-Dist: google-auth; extra == "full"
Requires-Dist: google-cloud-secret-manager; extra == "full"
Requires-Dist: google-cloud-storage; extra == "full"
Requires-Dist: grpc-google-iam-v1; extra == "full"
Requires-Dist: grpcio; extra == "full"
Requires-Dist: grpcio-status; extra == "full"
Requires-Dist: proto-plus; extra == "full"
Requires-Dist: protobuf; extra == "full"
Provides-Extra: dev
Requires-Dist: boto3; extra == "dev"
Requires-Dist: google-api-core; extra == "dev"
Requires-Dist: google-auth; extra == "dev"
Requires-Dist: google-cloud-secret-manager; extra == "dev"
Requires-Dist: google-cloud-storage; extra == "dev"
Requires-Dist: grpc-google-iam-v1; extra == "dev"
Requires-Dist: grpcio; extra == "dev"
Requires-Dist: grpcio-status; extra == "dev"
Requires-Dist: proto-plus; extra == "dev"
Requires-Dist: protobuf; extra == "dev"
Requires-Dist: black; extra == "dev"
Requires-Dist: ruff; extra == "dev"
Requires-Dist: pytest; extra == "dev"
Requires-Dist: pytest-cov; extra == "dev"
Requires-Dist: pytest-mock; extra == "dev"
Requires-Dist: coverage; extra == "dev"
